xiaomitv/__init__.py
xiaomitv-0.9.2.dist-info/LICENSE
xiaomitv-0.9.2.dist-info/METADATA
xiaomitv-0.9.2.dist-info/WHEEL
xiaomitv-0.9.2.dist-info/top_level.txt
xiaomitv-0.9.2.dist-info/RECORD
