Metadata-Version: 2.1
Name: xiaomitv
Version: 0.9.2
Summary: Remote control for Xiaomi TVs
Author-email: zhbjsh <zhbjsh@outlook.com>
Project-URL: Homepage, https://github.com/zhbjsh/xiaomitv
Project-URL: Bug Tracker, https://github.com/zhbjsh/xiaomitv/issues
Keywords: xiaomi tv,mi tv,xiaomi,remote control
Classifier: Programming Language :: Python :: 3.10
Classifier: License :: OSI Approved :: MIT License
Classifier: Operating System :: OS Independent
Requires-Python: >=3.10
License-File: LICENSE
Requires-Dist: aiohttp (>=3.8.5)
